{
  "generatedAt": "2026-06-12 02:22",
  "city": {
    "id": "beijing",
    "name": "北京市"
  },
  "poster": {
    "headline": "今天北京哪里柳絮最猛？",
    "dek": "全市已有 15 个区进入高风险，东城区 最值得警惕。",
    "topDistrict": {
      "id": "dongcheng",
      "name": "东城区",
      "score": 100,
      "level": {
        "key": "high",
        "label": "高风险"
      }
    },
    "updatedAt": "2026-06-12 02:22"
  },
  "topDistrict": {
    "id": "dongcheng",
    "name": "东城区",
    "score": 100,
    "level": {
      "key": "high",
      "label": "高风险"
    }
  },
  "defaultDistrictId": "dongcheng",
  "ranking": [
    {
      "id": "dongcheng",
      "name": "东城区",
      "shortName": "东城",
      "districtTag": "老城中轴",
      "districtHint": "胡同绿荫与中轴公园交织",
      "score": 100,
      "level": {
        "key": "high",
        "label": "高风险"
      },
      "ecologyMultiplier": 1.1,
      "rollingGdd": 36.8,
      "sunshineBoost": 1.16,
      "cloudPenalty": 0.93,
      "sunnyStreakBoost": 1
    },
    {
      "id": "xicheng",
      "name": "西城区",
      "shortName": "西城",
      "districtTag": "皇家园林",
      "districtHint": "湖面与老园林片区更要留意",
      "score": 100,
      "level": {
        "key": "high",
        "label": "高风险"
      },
      "ecologyMultiplier": 1.08,
      "rollingGdd": 39,
      "sunshineBoost": 1.16,
      "cloudPenalty": 0.93,
      "sunnyStreakBoost": 1
    },
    {
      "id": "chaoyang",
      "name": "朝阳区",
      "shortName": "朝阳",
      "districtTag": "大公园带",
      "districtHint": "朝阳公园和奥森周边最典型",
      "score": 100,
      "level": {
        "key": "high",
        "label": "高风险"
      },
      "ecologyMultiplier": 1.28,
      "rollingGdd": 38.2,
      "sunshineBoost": 1.16,
      "cloudPenalty": 1,
      "sunnyStreakBoost": 1
    },
    {
      "id": "haidian",
      "name": "海淀区",
      "shortName": "海淀",
      "districtTag": "园林高校带",
      "districtHint": "圆明园与植物园周边暴露更强",
      "score": 100,
      "level": {
        "key": "high",
        "label": "高风险"
      },
      "ecologyMultiplier": 1.24,
      "rollingGdd": 32.1,
      "sunshineBoost": 1.16,
      "cloudPenalty": 0.93,
      "sunnyStreakBoost": 1
    },
    {
      "id": "fengtai",
      "name": "丰台区",
      "shortName": "丰台",
      "districtTag": "南城绿博",
      "districtHint": "园博园与南苑绿地是重点片区",
      "score": 100,
      "level": {
        "key": "high",
        "label": "高风险"
      },
      "ecologyMultiplier": 1.15,
      "rollingGdd": 39.5,
      "sunshineBoost": 1.16,
      "cloudPenalty": 0.93,
      "sunnyStreakBoost": 1
    },
    {
      "id": "tongzhou",
      "name": "通州区",
      "shortName": "通州",
      "districtTag": "运河森林",
      "districtHint": "绿心与运河森林一带更敏感",
      "score": 100,
      "level": {
        "key": "high",
        "label": "高风险"
      },
      "ecologyMultiplier": 1.18,
      "rollingGdd": 35.9,
      "sunshineBoost": 1.16,
      "cloudPenalty": 1,
      "sunnyStreakBoost": 1
    },
    {
      "id": "shunyi",
      "name": "顺义区",
      "shortName": "顺义",
      "districtTag": "温榆水岸",
      "districtHint": "滨水绿带与开阔地更易感知",
      "score": 100,
      "level": {
        "key": "high",
        "label": "高风险"
      },
      "ecologyMultiplier": 1.06,
      "rollingGdd": 25.9,
      "sunshineBoost": 1.16,
      "cloudPenalty": 1,
      "sunnyStreakBoost": 1
    },
    {
      "id": "changping",
      "name": "昌平区",
      "shortName": "昌平",
      "districtTag": "北部开阔",
      "districtHint": "开阔地配阵风时扩散更快",
      "score": 100,
      "level": {
        "key": "high",
        "label": "高风险"
      },
      "ecologyMultiplier": 1.12,
      "rollingGdd": 30.1,
      "sunshineBoost": 1.16,
      "cloudPenalty": 0.93,
      "sunnyStreakBoost": 1
    },
    {
      "id": "daxing",
      "name": "大兴区",
      "shortName": "大兴",
      "districtTag": "南海湿地",
      "districtHint": "湿地周边雨后回升需关注",
      "score": 100,
      "level": {
        "key": "high",
        "label": "高风险"
      },
      "ecologyMultiplier": 1.12,
      "rollingGdd": 36.6,
      "sunshineBoost": 1.16,
      "cloudPenalty": 0.93,
      "sunnyStreakBoost": 1
    },
    {
      "id": "fangshan",
      "name": "房山区",
      "shortName": "房山",
      "districtTag": "河谷绿带",
      "districtHint": "河谷与新区绿化带更关键",
      "score": 100,
      "level": {
        "key": "high",
        "label": "高风险"
      },
      "ecologyMultiplier": 1.04,
      "rollingGdd": 37.7,
      "sunshineBoost": 1.16,
      "cloudPenalty": 0.93,
      "sunnyStreakBoost": 1
    },
    {
      "id": "pinggu",
      "name": "平谷区",
      "shortName": "平谷",
      "districtTag": "郊野开阔",
      "districtHint": "郊野开阔地受天气驱动更强",
      "score": 100,
      "level": {
        "key": "high",
        "label": "高风险"
      },
      "ecologyMultiplier": 0.93,
      "rollingGdd": 25,
      "sunshineBoost": 1.16,
      "cloudPenalty": 1,
      "sunnyStreakBoost": 1.06
    },
    {
      "id": "miyun",
      "name": "密云区",
      "shortName": "密云",
      "districtTag": "库区风场",
      "districtHint": "库区周边更看风与湿度变化",
      "score": 100,
      "level": {
        "key": "high",
        "label": "高风险"
      },
      "ecologyMultiplier": 0.94,
      "rollingGdd": 25.9,
      "sunshineBoost": 1.16,
      "cloudPenalty": 1,
      "sunnyStreakBoost": 1
    },
    {
      "id": "shijingshan",
      "name": "石景山区",
      "shortName": "石景山",
      "districtTag": "西山风口",
      "districtHint": "山前风口让飘散感更明显",
      "score": 98.9,
      "level": {
        "key": "high",
        "label": "高风险"
      },
      "ecologyMultiplier": 1.08,
      "rollingGdd": 34.6,
      "sunshineBoost": 1.16,
      "cloudPenalty": 0.93,
      "sunnyStreakBoost": 1
    },
    {
      "id": "mentougou",
      "name": "门头沟区",
      "shortName": "门头沟",
      "districtTag": "山谷通道",
      "districtHint": "山前通风通道影响体感强弱",
      "score": 89.7,
      "level": {
        "key": "high",
        "label": "高风险"
      },
      "ecologyMultiplier": 0.98,
      "rollingGdd": 28,
      "sunshineBoost": 1.16,
      "cloudPenalty": 0.93,
      "sunnyStreakBoost": 1
    },
    {
      "id": "huairou",
      "name": "怀柔区",
      "shortName": "怀柔",
      "districtTag": "湖区林地",
      "districtHint": "湖区林地局部波动更大",
      "score": 62.9,
      "level": {
        "key": "high",
        "label": "高风险"
      },
      "ecologyMultiplier": 0.95,
      "rollingGdd": 21.7,
      "sunshineBoost": 1.16,
      "cloudPenalty": 0.93,
      "sunnyStreakBoost": 1
    },
    {
      "id": "yanqing",
      "name": "延庆区",
      "shortName": "延庆",
      "districtTag": "高地晴风",
      "districtHint": "高地晴天阵风会放大飘散感",
      "score": 29.1,
      "level": {
        "key": "low",
        "label": "低风险"
      },
      "ecologyMultiplier": 0.91,
      "rollingGdd": 8.8,
      "sunshineBoost": 1.16,
      "cloudPenalty": 0.93,
      "sunnyStreakBoost": 1
    }
  ],
  "districts": [
    {
      "id": "dongcheng",
      "name": "东城区",
      "shortName": "东城",
      "districtTag": "老城中轴",
      "districtHint": "胡同绿荫与中轴公园交织",
      "score": 100,
      "level": {
        "key": "high",
        "label": "高风险"
      },
      "weather": {
        "date": "2026-06-12",
        "temperatureMax": 34.9,
        "temperatureMin": 21.7,
        "temperatureMean": 28.8,
        "humidity": 35,
        "humidityMin": 21,
        "windSpeed": 5.6,
        "windGust": 11.5,
        "precipitation": 1.1,
        "recentPrecipitation": 4.9,
        "sunshineDuration": 37843,
        "shortwaveRadiationSum": 23,
        "cloudCoverMean": 57,
        "rollingTemperatureMeans": [
          21.5,
          21.1,
          25.4,
          28.8
        ],
        "recentConditions": [
          {
            "date": "2026-06-09",
            "sunshineDuration": 48836,
            "cloudCoverMean": 14
          },
          {
            "date": "2026-06-10",
            "sunshineDuration": 43610,
            "cloudCoverMean": 48
          },
          {
            "date": "2026-06-11",
            "sunshineDuration": 49336,
            "cloudCoverMean": 8
          },
          {
            "date": "2026-06-12",
            "sunshineDuration": 37843,
            "cloudCoverMean": 57
          }
        ]
      },
      "weatherScore": 100,
      "rollingGdd": 36.8,
      "gddBoost": 1.18,
      "precipitationPenalty": 0.78,
      "drynessWindBoost": 1.16,
      "sunshineBoost": 1.16,
      "cloudPenalty": 0.93,
      "sunnyStreakBoost": 1,
      "ecologyMultiplier": 1.1,
      "hotspots": [
        "景山公园",
        "龙潭中湖公园",
        "明城墙遗址公园"
      ],
      "advice": "建议减少外出，尤其注意大型公园、滨河绿地和午后风口区域；外出请做好口鼻防护。",
      "headline": "东城区当前以气象条件和区级生态暴露驱动为主。",
      "tomorrow": {
        "score": 82,
        "level": {
          "key": "high",
          "label": "高风险"
        },
        "weather": {
          "date": "2026-06-13",
          "temperatureMax": 29.9,
          "temperatureMin": 20.6,
          "temperatureMean": 24.3,
          "humidity": 64,
          "humidityMin": 42,
          "windSpeed": 3,
          "windGust": 12.3,
          "precipitation": 2,
          "recentPrecipitation": 1.1,
          "sunshineDuration": 35016,
          "shortwaveRadiationSum": 18.8,
          "cloudCoverMean": 79,
          "rollingTemperatureMeans": [
            21.1,
            25.4,
            28.8,
            24.3
          ],
          "recentConditions": [
            {
              "date": "2026-06-10",
              "sunshineDuration": 43610,
              "cloudCoverMean": 48
            },
            {
              "date": "2026-06-11",
              "sunshineDuration": 49336,
              "cloudCoverMean": 8
            },
            {
              "date": "2026-06-12",
              "sunshineDuration": 37843,
              "cloudCoverMean": 57
            },
            {
              "date": "2026-06-13",
              "sunshineDuration": 35016,
              "cloudCoverMean": 79
            }
          ]
        },
        "weatherScore": 65.1,
        "rollingGdd": 39.6,
        "gddBoost": 1.18,
        "precipitationPenalty": 0.9,
        "drynessWindBoost": 1.12,
        "sunshineBoost": 1.12,
        "cloudPenalty": 0.86,
        "sunnyStreakBoost": 1,
        "ecologyMultiplier": 1.1,
        "advice": "建议减少外出，尤其注意大型公园、滨河绿地和午后风口区域；外出请做好口鼻防护。"
      },
      "dayAfterTomorrow": {
        "score": 84.3,
        "level": {
          "key": "high",
          "label": "高风险"
        },
        "weather": {
          "date": "2026-06-14",
          "temperatureMax": 30.1,
          "temperatureMin": 19.7,
          "temperatureMean": 24.5,
          "humidity": 70,
          "humidityMin": 46,
          "windSpeed": 4.1,
          "windGust": 9,
          "precipitation": 2.3,
          "recentPrecipitation": 3.1,
          "sunshineDuration": 47337,
          "shortwaveRadiationSum": 25.1,
          "cloudCoverMean": 40,
          "rollingTemperatureMeans": [
            25.4,
            28.8,
            24.3,
            24.5
          ],
          "recentConditions": [
            {
              "date": "2026-06-11",
              "sunshineDuration": 49336,
              "cloudCoverMean": 8
            },
            {
              "date": "2026-06-12",
              "sunshineDuration": 37843,
              "cloudCoverMean": 57
            },
            {
              "date": "2026-06-13",
              "sunshineDuration": 35016,
              "cloudCoverMean": 79
            },
            {
              "date": "2026-06-14",
              "sunshineDuration": 47337,
              "cloudCoverMean": 40
            }
          ]
        },
        "weatherScore": 66.5,
        "rollingGdd": 43,
        "gddBoost": 1.18,
        "precipitationPenalty": 0.78,
        "drynessWindBoost": 1.08,
        "sunshineBoost": 1.16,
        "cloudPenalty": 1,
        "sunnyStreakBoost": 1,
        "ecologyMultiplier": 1.1,
        "advice": "建议减少外出，尤其注意大型公园、滨河绿地和午后风口区域；外出请做好口鼻防护。"
      }
    },
    {
      "id": "xicheng",
      "name": "西城区",
      "shortName": "西城",
      "districtTag": "皇家园林",
      "districtHint": "湖面与老园林片区更要留意",
      "score": 100,
      "level": {
        "key": "high",
        "label": "高风险"
      },
      "weather": {
        "date": "2026-06-12",
        "temperatureMax": 34.8,
        "temperatureMin": 22.3,
        "temperatureMean": 29.1,
        "humidity": 35,
        "humidityMin": 22,
        "windSpeed": 4,
        "windGust": 10.4,
        "precipitation": 1.2,
        "recentPrecipitation": 3.5,
        "sunshineDuration": 39865,
        "shortwaveRadiationSum": 23.2,
        "cloudCoverMean": 56,
        "rollingTemperatureMeans": [
          22.6,
          21.8,
          25.5,
          29.1
        ],
        "recentConditions": [
          {
            "date": "2026-06-09",
            "sunshineDuration": 49125,
            "cloudCoverMean": 9
          },
          {
            "date": "2026-06-10",
            "sunshineDuration": 44460,
            "cloudCoverMean": 47
          },
          {
            "date": "2026-06-11",
            "sunshineDuration": 49629,
            "cloudCoverMean": 7
          },
          {
            "date": "2026-06-12",
            "sunshineDuration": 39865,
            "cloudCoverMean": 56
          }
        ]
      },
      "weatherScore": 100,
      "rollingGdd": 39,
      "gddBoost": 1.18,
      "precipitationPenalty": 0.78,
      "drynessWindBoost": 1.16,
      "sunshineBoost": 1.16,
      "cloudPenalty": 0.93,
      "sunnyStreakBoost": 1,
      "ecologyMultiplier": 1.08,
      "hotspots": [
        "北海公园",
        "月坛公园",
        "陶然亭公园"
      ],
      "advice": "建议减少外出，尤其注意大型公园、滨河绿地和午后风口区域；外出请做好口鼻防护。",
      "headline": "西城区当前以气象条件和区级生态暴露驱动为主。",
      "tomorrow": {
        "score": 80.4,
        "level": {
          "key": "high",
          "label": "高风险"
        },
        "weather": {
          "date": "2026-06-13",
          "temperatureMax": 30.3,
          "temperatureMin": 21.3,
          "temperatureMean": 24.9,
          "humidity": 61,
          "humidityMin": 41,
          "windSpeed": 2.9,
          "windGust": 13.4,
          "precipitation": 3,
          "recentPrecipitation": 1.2,
          "sunshineDuration": 34339,
          "shortwaveRadiationSum": 19.4,
          "cloudCoverMean": 74,
          "rollingTemperatureMeans": [
            21.8,
            25.5,
            29.1,
            24.9
          ],
          "recentConditions": [
            {
              "date": "2026-06-10",
              "sunshineDuration": 44460,
              "cloudCoverMean": 47
            },
            {
              "date": "2026-06-11",
              "sunshineDuration": 49629,
              "cloudCoverMean": 7
            },
            {
              "date": "2026-06-12",
              "sunshineDuration": 39865,
              "cloudCoverMean": 56
            },
            {
              "date": "2026-06-13",
              "sunshineDuration": 34339,
              "cloudCoverMean": 74
            }
          ]
        },
        "weatherScore": 69.3,
        "rollingGdd": 41.3,
        "gddBoost": 1.18,
        "precipitationPenalty": 0.78,
        "drynessWindBoost": 1.12,
        "sunshineBoost": 1.12,
        "cloudPenalty": 0.93,
        "sunnyStreakBoost": 1,
        "ecologyMultiplier": 1.08,
        "advice": "建议减少外出，尤其注意大型公园、滨河绿地和午后风口区域；外出请做好口鼻防护。"
      },
      "dayAfterTomorrow": {
        "score": 90.4,
        "level": {
          "key": "high",
          "label": "高风险"
        },
        "weather": {
          "date": "2026-06-14",
          "temperatureMax": 30.8,
          "temperatureMin": 20.5,
          "temperatureMean": 25,
          "humidity": 66,
          "humidityMin": 41,
          "windSpeed": 2.7,
          "windGust": 8.6,
          "precipitation": 2.2,
          "recentPrecipitation": 4.2,
          "sunshineDuration": 47337,
          "shortwaveRadiationSum": 25.2,
          "cloudCoverMean": 45,
          "rollingTemperatureMeans": [
            25.5,
            29.1,
            24.9,
            25
          ],
          "recentConditions": [
            {
              "date": "2026-06-11",
              "sunshineDuration": 49629,
              "cloudCoverMean": 7
            },
            {
              "date": "2026-06-12",
              "sunshineDuration": 39865,
              "cloudCoverMean": 56
            },
            {
              "date": "2026-06-13",
              "sunshineDuration": 34339,
              "cloudCoverMean": 74
            },
            {
              "date": "2026-06-14",
              "sunshineDuration": 47337,
              "cloudCoverMean": 45
            }
          ]
        },
        "weatherScore": 70,
        "rollingGdd": 44.5,
        "gddBoost": 1.18,
        "precipitationPenalty": 0.78,
        "drynessWindBoost": 1.12,
        "sunshineBoost": 1.16,
        "cloudPenalty": 1,
        "sunnyStreakBoost": 1,
        "ecologyMultiplier": 1.08,
        "advice": "建议减少外出，尤其注意大型公园、滨河绿地和午后风口区域；外出请做好口鼻防护。"
      }
    },
    {
      "id": "chaoyang",
      "name": "朝阳区",
      "shortName": "朝阳",
      "districtTag": "大公园带",
      "districtHint": "朝阳公园和奥森周边最典型",
      "score": 100,
      "level": {
        "key": "high",
        "label": "高风险"
      },
      "weather": {
        "date": "2026-06-12",
        "temperatureMax": 34.7,
        "temperatureMin": 22.9,
        "temperatureMean": 29.2,
        "humidity": 35,
        "humidityMin": 21,
        "windSpeed": 4.1,
        "windGust": 9.7,
        "precipitation": 0.1,
        "recentPrecipitation": 5.6,
        "sunshineDuration": 40283,
        "shortwaveRadiationSum": 23.2,
        "cloudCoverMean": 54,
        "rollingTemperatureMeans": [
          21.7,
          21.6,
          25.7,
          29.2
        ],
        "recentConditions": [
          {
            "date": "2026-06-09",
            "sunshineDuration": 48963,
            "cloudCoverMean": 12
          },
          {
            "date": "2026-06-10",
            "sunshineDuration": 42735,
            "cloudCoverMean": 51
          },
          {
            "date": "2026-06-11",
            "sunshineDuration": 49570,
            "cloudCoverMean": 7
          },
          {
            "date": "2026-06-12",
            "sunshineDuration": 40283,
            "cloudCoverMean": 54
          }
        ]
      },
      "weatherScore": 100,
      "rollingGdd": 38.2,
      "gddBoost": 1.18,
      "precipitationPenalty": 0.78,
      "drynessWindBoost": 1.16,
      "sunshineBoost": 1.16,
      "cloudPenalty": 1,
      "sunnyStreakBoost": 1,
      "ecologyMultiplier": 1.28,
      "hotspots": [
        "朝阳公园",
        "奥林匹克森林公园",
        "温榆河公园"
      ],
      "advice": "建议减少外出，尤其注意大型公园、滨河绿地和午后风口区域；外出请做好口鼻防护。",
      "headline": "朝阳区当前以气象条件和区级生态暴露驱动为主。",
      "tomorrow": {
        "score": 100,
        "level": {
          "key": "high",
          "label": "高风险"
        },
        "weather": {
          "date": "2026-06-13",
          "temperatureMax": 29.9,
          "temperatureMin": 20.8,
          "temperatureMean": 24.9,
          "humidity": 61,
          "humidityMin": 42,
          "windSpeed": 3.2,
          "windGust": 10.2,
          "precipitation": 1.7,
          "recentPrecipitation": 0.1,
          "sunshineDuration": 35729,
          "shortwaveRadiationSum": 19.6,
          "cloudCoverMean": 71,
          "rollingTemperatureMeans": [
            21.6,
            25.7,
            29.2,
            24.9
          ],
          "recentConditions": [
            {
              "date": "2026-06-10",
              "sunshineDuration": 42735,
              "cloudCoverMean": 51
            },
            {
              "date": "2026-06-11",
              "sunshineDuration": 49570,
              "cloudCoverMean": 7
            },
            {
              "date": "2026-06-12",
              "sunshineDuration": 40283,
              "cloudCoverMean": 54
            },
            {
              "date": "2026-06-13",
              "sunshineDuration": 35729,
              "cloudCoverMean": 71
            }
          ]
        },
        "weatherScore": 69.3,
        "rollingGdd": 41.4,
        "gddBoost": 1.18,
        "precipitationPenalty": 0.9,
        "drynessWindBoost": 1.12,
        "sunshineBoost": 1.12,
        "cloudPenalty": 0.93,
        "sunnyStreakBoost": 1,
        "ecologyMultiplier": 1.28,
        "advice": "建议减少外出，尤其注意大型公园、滨河绿地和午后风口区域；外出请做好口鼻防护。"
      },
      "dayAfterTomorrow": {
        "score": 100,
        "level": {
          "key": "high",
          "label": "高风险"
        },
        "weather": {
          "date": "2026-06-14",
          "temperatureMax": 30.4,
          "temperatureMin": 20.3,
          "temperatureMean": 24.7,
          "humidity": 68,
          "humidityMin": 43,
          "windSpeed": 4.4,
          "windGust": 9.1,
          "precipitation": 3,
          "recentPrecipitation": 1.8,
          "sunshineDuration": 47352,
          "shortwaveRadiationSum": 25.1,
          "cloudCoverMean": 46,
          "rollingTemperatureMeans": [
            25.7,
            29.2,
            24.9,
            24.7
          ],
          "recentConditions": [
            {
              "date": "2026-06-11",
              "sunshineDuration": 49570,
              "cloudCoverMean": 7
            },
            {
              "date": "2026-06-12",
              "sunshineDuration": 40283,
              "cloudCoverMean": 54
            },
            {
              "date": "2026-06-13",
              "sunshineDuration": 35729,
              "cloudCoverMean": 71
            },
            {
              "date": "2026-06-14",
              "sunshineDuration": 47352,
              "cloudCoverMean": 46
            }
          ]
        },
        "weatherScore": 67.9,
        "rollingGdd": 44.5,
        "gddBoost": 1.18,
        "precipitationPenalty": 0.78,
        "drynessWindBoost": 1.12,
        "sunshineBoost": 1.16,
        "cloudPenalty": 1,
        "sunnyStreakBoost": 1,
        "ecologyMultiplier": 1.28,
        "advice": "建议减少外出，尤其注意大型公园、滨河绿地和午后风口区域；外出请做好口鼻防护。"
      }
    },
    {
      "id": "haidian",
      "name": "海淀区",
      "shortName": "海淀",
      "districtTag": "园林高校带",
      "districtHint": "圆明园与植物园周边暴露更强",
      "score": 100,
      "level": {
        "key": "high",
        "label": "高风险"
      },
      "weather": {
        "date": "2026-06-12",
        "temperatureMax": 34.4,
        "temperatureMin": 18.7,
        "temperatureMean": 27,
        "humidity": 42,
        "humidityMin": 22,
        "windSpeed": 4.8,
        "windGust": 10.6,
        "precipitation": 1.5,
        "recentPrecipitation": 6.5,
        "sunshineDuration": 36591,
        "shortwaveRadiationSum": 23,
        "cloudCoverMean": 58,
        "rollingTemperatureMeans": [
          20.9,
          20.1,
          24.1,
          27
        ],
        "recentConditions": [
          {
            "date": "2026-06-09",
            "sunshineDuration": 49159,
            "cloudCoverMean": 11
          },
          {
            "date": "2026-06-10",
            "sunshineDuration": 44408,
            "cloudCoverMean": 45
          },
          {
            "date": "2026-06-11",
            "sunshineDuration": 49651,
            "cloudCoverMean": 9
          },
          {
            "date": "2026-06-12",
            "sunshineDuration": 36591,
            "cloudCoverMean": 58
          }
        ]
      },
      "weatherScore": 100,
      "rollingGdd": 32.1,
      "gddBoost": 1.18,
      "precipitationPenalty": 0.62,
      "drynessWindBoost": 1.16,
      "sunshineBoost": 1.16,
      "cloudPenalty": 0.93,
      "sunnyStreakBoost": 1,
      "ecologyMultiplier": 1.24,
      "hotspots": [
        "颐和园",
        "圆明园",
        "国家植物园"
      ],
      "advice": "建议减少外出，尤其注意大型公园、滨河绿地和午后风口区域；外出请做好口鼻防护。",
      "headline": "海淀区当前以气象条件和区级生态暴露驱动为主。",
      "tomorrow": {
        "score": 71.5,
        "level": {
          "key": "high",
          "label": "高风险"
        },
        "weather": {
          "date": "2026-06-13",
          "temperatureMax": 29,
          "temperatureMin": 20.1,
          "temperatureMean": 23.6,
          "humidity": 68,
          "humidityMin": 46,
          "windSpeed": 2.4,
          "windGust": 10.8,
          "precipitation": 3,
          "recentPrecipitation": 1.5,
          "sunshineDuration": 33858,
          "shortwaveRadiationSum": 18.6,
          "cloudCoverMean": 78,
          "rollingTemperatureMeans": [
            20.1,
            24.1,
            27,
            23.6
          ],
          "recentConditions": [
            {
              "date": "2026-06-10",
              "sunshineDuration": 44408,
              "cloudCoverMean": 45
            },
            {
              "date": "2026-06-11",
              "sunshineDuration": 49651,
              "cloudCoverMean": 9
            },
            {
              "date": "2026-06-12",
              "sunshineDuration": 36591,
              "cloudCoverMean": 58
            },
            {
              "date": "2026-06-13",
              "sunshineDuration": 33858,
              "cloudCoverMean": 78
            }
          ]
        },
        "weatherScore": 60.2,
        "rollingGdd": 34.8,
        "gddBoost": 1.18,
        "precipitationPenalty": 0.78,
        "drynessWindBoost": 1.08,
        "sunshineBoost": 1.12,
        "cloudPenalty": 0.86,
        "sunnyStreakBoost": 1,
        "ecologyMultiplier": 1.24,
        "advice": "建议减少外出，尤其注意大型公园、滨河绿地和午后风口区域；外出请做好口鼻防护。"
      },
      "dayAfterTomorrow": {
        "score": 93.4,
        "level": {
          "key": "high",
          "label": "高风险"
        },
        "weather": {
          "date": "2026-06-14",
          "temperatureMax": 29.7,
          "temperatureMin": 19.1,
          "temperatureMean": 24,
          "humidity": 72,
          "humidityMin": 45,
          "windSpeed": 1.9,
          "windGust": 8.4,
          "precipitation": 2.2,
          "recentPrecipitation": 4.5,
          "sunshineDuration": 47476,
          "shortwaveRadiationSum": 24.9,
          "cloudCoverMean": 45,
          "rollingTemperatureMeans": [
            24.1,
            27,
            23.6,
            24
          ],
          "recentConditions": [
            {
              "date": "2026-06-11",
              "sunshineDuration": 49651,
              "cloudCoverMean": 9
            },
            {
              "date": "2026-06-12",
              "sunshineDuration": 36591,
              "cloudCoverMean": 58
            },
            {
              "date": "2026-06-13",
              "sunshineDuration": 33858,
              "cloudCoverMean": 78
            },
            {
              "date": "2026-06-14",
              "sunshineDuration": 47476,
              "cloudCoverMean": 45
            }
          ]
        },
        "weatherScore": 63,
        "rollingGdd": 38.7,
        "gddBoost": 1.18,
        "precipitationPenalty": 0.78,
        "drynessWindBoost": 1.12,
        "sunshineBoost": 1.16,
        "cloudPenalty": 1,
        "sunnyStreakBoost": 1,
        "ecologyMultiplier": 1.24,
        "advice": "建议减少外出，尤其注意大型公园、滨河绿地和午后风口区域；外出请做好口鼻防护。"
      }
    },
    {
      "id": "fengtai",
      "name": "丰台区",
      "shortName": "丰台",
      "districtTag": "南城绿博",
      "districtHint": "园博园与南苑绿地是重点片区",
      "score": 100,
      "level": {
        "key": "high",
        "label": "高风险"
      },
      "weather": {
        "date": "2026-06-12",
        "temperatureMax": 34.9,
        "temperatureMin": 22.2,
        "temperatureMean": 29.1,
        "humidity": 36,
        "humidityMin": 22,
        "windSpeed": 5.4,
        "windGust": 10.4,
        "precipitation": 0.2,
        "recentPrecipitation": 4.2,
        "sunshineDuration": 41929,
        "shortwaveRadiationSum": 23.4,
        "cloudCoverMean": 58,
        "rollingTemperatureMeans": [
          22.9,
          22.1,
          25.4,
          29.1
        ],
        "recentConditions": [
          {
            "date": "2026-06-09",
            "sunshineDuration": 49009,
            "cloudCoverMean": 11
          },
          {
            "date": "2026-06-10",
            "sunshineDuration": 45858,
            "cloudCoverMean": 46
          },
          {
            "date": "2026-06-11",
            "sunshineDuration": 49408,
            "cloudCoverMean": 9
          },
          {
            "date": "2026-06-12",
            "sunshineDuration": 41929,
            "cloudCoverMean": 58
          }
        ]
      },
      "weatherScore": 100,
      "rollingGdd": 39.5,
      "gddBoost": 1.18,
      "precipitationPenalty": 0.78,
      "drynessWindBoost": 1.16,
      "sunshineBoost": 1.16,
      "cloudPenalty": 0.93,
      "sunnyStreakBoost": 1,
      "ecologyMultiplier": 1.15,
      "hotspots": [
        "园博园",
        "南苑森林湿地公园",
        "世界花卉大观园"
      ],
      "advice": "建议减少外出，尤其注意大型公园、滨河绿地和午后风口区域；外出请做好口鼻防护。",
      "headline": "丰台区当前以气象条件和区级生态暴露驱动为主。",
      "tomorrow": {
        "score": 100,
        "level": {
          "key": "high",
          "label": "高风险"
        },
        "weather": {
          "date": "2026-06-13",
          "temperatureMax": 30.5,
          "temperatureMin": 21.6,
          "temperatureMean": 25.3,
          "humidity": 59,
          "humidityMin": 41,
          "windSpeed": 3.4,
          "windGust": 12.5,
          "precipitation": 2.6,
          "recentPrecipitation": 0.2,
          "sunshineDuration": 36445,
          "shortwaveRadiationSum": 20,
          "cloudCoverMean": 75,
          "rollingTemperatureMeans": [
            22.1,
            25.4,
            29.1,
            25.3
          ],
          "recentConditions": [
            {
              "date": "2026-06-10",
              "sunshineDuration": 45858,
              "cloudCoverMean": 46
            },
            {
              "date": "2026-06-11",
              "sunshineDuration": 49408,
              "cloudCoverMean": 9
            },
            {
              "date": "2026-06-12",
              "sunshineDuration": 41929,
              "cloudCoverMean": 58
            },
            {
              "date": "2026-06-13",
              "sunshineDuration": 36445,
              "cloudCoverMean": 75
            }
          ]
        },
        "weatherScore": 100,
        "rollingGdd": 41.9,
        "gddBoost": 1.18,
        "precipitationPenalty": 0.9,
        "drynessWindBoost": 1.12,
        "sunshineBoost": 1.16,
        "cloudPenalty": 0.86,
        "sunnyStreakBoost": 1,
        "ecologyMultiplier": 1.15,
        "advice": "建议减少外出，尤其注意大型公园、滨河绿地和午后风口区域；外出请做好口鼻防护。"
      },
      "dayAfterTomorrow": {
        "score": 100,
        "level": {
          "key": "high",
          "label": "高风险"
        },
        "weather": {
          "date": "2026-06-14",
          "temperatureMax": 31.3,
          "temperatureMin": 20.6,
          "temperatureMean": 25.4,
          "humidity": 64,
          "humidityMin": 39,
          "windSpeed": 2.6,
          "windGust": 9.8,
          "precipitation": 2.5,
          "recentPrecipitation": 2.8,
          "sunshineDuration": 47337,
          "shortwaveRadiationSum": 25.2,
          "cloudCoverMean": 41,
          "rollingTemperatureMeans": [
            25.4,
            29.1,
            25.3,
            25.4
          ],
          "recentConditions": [
            {
              "date": "2026-06-11",
              "sunshineDuration": 49408,
              "cloudCoverMean": 9
            },
            {
              "date": "2026-06-12",
              "sunshineDuration": 41929,
              "cloudCoverMean": 58
            },
            {
              "date": "2026-06-13",
              "sunshineDuration": 36445,
              "cloudCoverMean": 75
            },
            {
              "date": "2026-06-14",
              "sunshineDuration": 47337,
              "cloudCoverMean": 41
            }
          ]
        },
        "weatherScore": 72.8,
        "rollingGdd": 45.2,
        "gddBoost": 1.18,
        "precipitationPenalty": 0.78,
        "drynessWindBoost": 1.12,
        "sunshineBoost": 1.16,
        "cloudPenalty": 1,
        "sunnyStreakBoost": 1,
        "ecologyMultiplier": 1.15,
        "advice": "建议减少外出，尤其注意大型公园、滨河绿地和午后风口区域；外出请做好口鼻防护。"
      }
    },
    {
      "id": "tongzhou",
      "name": "通州区",
      "shortName": "通州",
      "districtTag": "运河森林",
      "districtHint": "绿心与运河森林一带更敏感",
      "score": 100,
      "level": {
        "key": "high",
        "label": "高风险"
      },
      "weather": {
        "date": "2026-06-12",
        "temperatureMax": 34.5,
        "temperatureMin": 21.9,
        "temperatureMean": 28.6,
        "humidity": 38,
        "humidityMin": 22,
        "windSpeed": 4.6,
        "windGust": 10.4,
        "precipitation": 0,
        "recentPrecipitation": 2.7,
        "sunshineDuration": 41126,
        "shortwaveRadiationSum": 23.2,
        "cloudCoverMean": 52,
        "rollingTemperatureMeans": [
          21.1,
          21,
          25.2,
          28.6
        ],
        "recentConditions": [
          {
            "date": "2026-06-09",
            "sunshineDuration": 48496,
            "cloudCoverMean": 15
          },
          {
            "date": "2026-06-10",
            "sunshineDuration": 41219,
            "cloudCoverMean": 54
          },
          {
            "date": "2026-06-11",
            "sunshineDuration": 49512,
            "cloudCoverMean": 8
          },
          {
            "date": "2026-06-12",
            "sunshineDuration": 41126,
            "cloudCoverMean": 52
          }
        ]
      },
      "weatherScore": 100,
      "rollingGdd": 35.9,
      "gddBoost": 1.18,
      "precipitationPenalty": 0.9,
      "drynessWindBoost": 1.16,
      "sunshineBoost": 1.16,
      "cloudPenalty": 1,
      "sunnyStreakBoost": 1,
      "ecologyMultiplier": 1.18,
      "hotspots": [
        "城市绿心森林公园",
        "大运河森林公园"
      ],
      "advice": "建议减少外出，尤其注意大型公园、滨河绿地和午后风口区域；外出请做好口鼻防护。",
      "headline": "通州区当前以气象条件和区级生态暴露驱动为主。",
      "tomorrow": {
        "score": 95.2,
        "level": {
          "key": "high",
          "label": "高风险"
        },
        "weather": {
          "date": "2026-06-13",
          "temperatureMax": 29.8,
          "temperatureMin": 20.1,
          "temperatureMean": 24.3,
          "humidity": 64,
          "humidityMin": 42,
          "windSpeed": 3.6,
          "windGust": 10.1,
          "precipitation": 2.3,
          "recentPrecipitation": 0,
          "sunshineDuration": 36186,
          "shortwaveRadiationSum": 19.7,
          "cloudCoverMean": 74,
          "rollingTemperatureMeans": [
            21,
            25.2,
            28.6,
            24.3
          ],
          "recentConditions": [
            {
              "date": "2026-06-10",
              "sunshineDuration": 41219,
              "cloudCoverMean": 54
            },
            {
              "date": "2026-06-11",
              "sunshineDuration": 49512,
              "cloudCoverMean": 8
            },
            {
              "date": "2026-06-12",
              "sunshineDuration": 41126,
              "cloudCoverMean": 52
            },
            {
              "date": "2026-06-13",
              "sunshineDuration": 36186,
              "cloudCoverMean": 74
            }
          ]
        },
        "weatherScore": 65.1,
        "rollingGdd": 39.1,
        "gddBoost": 1.18,
        "precipitationPenalty": 0.9,
        "drynessWindBoost": 1.12,
        "sunshineBoost": 1.12,
        "cloudPenalty": 0.93,
        "sunnyStreakBoost": 1,
        "ecologyMultiplier": 1.18,
        "advice": "建议减少外出，尤其注意大型公园、滨河绿地和午后风口区域；外出请做好口鼻防护。"
      },
      "dayAfterTomorrow": {
        "score": 91.9,
        "level": {
          "key": "high",
          "label": "高风险"
        },
        "weather": {
          "date": "2026-06-14",
          "temperatureMax": 30.1,
          "temperatureMin": 19.6,
          "temperatureMean": 24.3,
          "humidity": 70,
          "humidityMin": 45,
          "windSpeed": 4.4,
          "windGust": 10.2,
          "precipitation": 1.9,
          "recentPrecipitation": 2.3,
          "sunshineDuration": 47368,
          "shortwaveRadiationSum": 24.7,
          "cloudCoverMean": 42,
          "rollingTemperatureMeans": [
            25.2,
            28.6,
            24.3,
            24.3
          ],
          "recentConditions": [
            {
              "date": "2026-06-11",
              "sunshineDuration": 49512,
              "cloudCoverMean": 8
            },
            {
              "date": "2026-06-12",
              "sunshineDuration": 41126,
              "cloudCoverMean": 52
            },
            {
              "date": "2026-06-13",
              "sunshineDuration": 36186,
              "cloudCoverMean": 74
            },
            {
              "date": "2026-06-14",
              "sunshineDuration": 47368,
              "cloudCoverMean": 42
            }
          ]
        },
        "weatherScore": 65.1,
        "rollingGdd": 42.4,
        "gddBoost": 1.18,
        "precipitationPenalty": 0.78,
        "drynessWindBoost": 1.12,
        "sunshineBoost": 1.16,
        "cloudPenalty": 1,
        "sunnyStreakBoost": 1,
        "ecologyMultiplier": 1.18,
        "advice": "建议减少外出，尤其注意大型公园、滨河绿地和午后风口区域；外出请做好口鼻防护。"
      }
    },
    {
      "id": "shunyi",
      "name": "顺义区",
      "shortName": "顺义",
      "districtTag": "温榆水岸",
      "districtHint": "滨水绿带与开阔地更易感知",
      "score": 100,
      "level": {
        "key": "high",
        "label": "高风险"
      },
      "weather": {
        "date": "2026-06-12",
        "temperatureMax": 33.4,
        "temperatureMin": 16.6,
        "temperatureMean": 25.5,
        "humidity": 50,
        "humidityMin": 26,
        "windSpeed": 5,
        "windGust": 10.7,
        "precipitation": 0,
        "recentPrecipitation": 11.4,
        "sunshineDuration": 44500,
        "shortwaveRadiationSum": 23.9,
        "cloudCoverMean": 51,
        "rollingTemperatureMeans": [
          19.5,
          18.9,
          22,
          25.5
        ],
        "recentConditions": [
          {
            "date": "2026-06-09",
            "sunshineDuration": 47866,
            "cloudCoverMean": 22
          },
          {
            "date": "2026-06-10",
            "sunshineDuration": 42275,
            "cloudCoverMean": 69
          },
          {
            "date": "2026-06-11",
            "sunshineDuration": 49427,
            "cloudCoverMean": 11
          },
          {
            "date": "2026-06-12",
            "sunshineDuration": 44500,
            "cloudCoverMean": 51
          }
        ]
      },
      "weatherScore": 100,
      "rollingGdd": 25.9,
      "gddBoost": 1.18,
      "precipitationPenalty": 0.62,
      "drynessWindBoost": 1.16,
      "sunshineBoost": 1.16,
      "cloudPenalty": 1,
      "sunnyStreakBoost": 1,
      "ecologyMultiplier": 1.06,
      "hotspots": [
        "奥林匹克水上公园",
        "温榆河沿线绿地"
      ],
      "advice": "建议减少外出，尤其注意大型公园、滨河绿地和午后风口区域；外出请做好口鼻防护。",
      "headline": "顺义区当前以气象条件和区级生态暴露驱动为主。",
      "tomorrow": {
        "score": 51.9,
        "level": {
          "key": "medium",
          "label": "中风险"
        },
        "weather": {
          "date": "2026-06-13",
          "temperatureMax": 27.3,
          "temperatureMin": 18.5,
          "temperatureMean": 22.3,
          "humidity": 78,
          "humidityMin": 55,
          "windSpeed": 4.6,
          "windGust": 9.6,
          "precipitation": 4.9,
          "recentPrecipitation": 0,
          "sunshineDuration": 33683,
          "shortwaveRadiationSum": 17.7,
          "cloudCoverMean": 84,
          "rollingTemperatureMeans": [
            18.9,
            22,
            25.5,
            22.3
          ],
          "recentConditions": [
            {
              "date": "2026-06-10",
              "sunshineDuration": 42275,
              "cloudCoverMean": 69
            },
            {
              "date": "2026-06-11",
              "sunshineDuration": 49427,
              "cloudCoverMean": 11
            },
            {
              "date": "2026-06-12",
              "sunshineDuration": 44500,
              "cloudCoverMean": 51
            },
            {
              "date": "2026-06-13",
              "sunshineDuration": 33683,
              "cloudCoverMean": 84
            }
          ]
        },
        "weatherScore": 51.1,
        "rollingGdd": 28.7,
        "gddBoost": 1.18,
        "precipitationPenalty": 0.78,
        "drynessWindBoost": 1.08,
        "sunshineBoost": 1.12,
        "cloudPenalty": 0.86,
        "sunnyStreakBoost": 1,
        "ecologyMultiplier": 1.06,
        "advice": "建议避开 10:00-16:00 的长时间户外停留，经过公园或林地边缘时做好基础防护。"
      },
      "dayAfterTomorrow": {
        "score": 70.2,
        "level": {
          "key": "high",
          "label": "高风险"
        },
        "weather": {
          "date": "2026-06-14",
          "temperatureMax": 29,
          "temperatureMin": 18.3,
          "temperatureMean": 23.2,
          "humidity": 78,
          "humidityMin": 51,
          "windSpeed": 3.8,
          "windGust": 8.4,
          "precipitation": 3,
          "recentPrecipitation": 4.9,
          "sunshineDuration": 48383,
          "shortwaveRadiationSum": 25.2,
          "cloudCoverMean": 36,
          "rollingTemperatureMeans": [
            22,
            25.5,
            22.3,
            23.2
          ],
          "recentConditions": [
            {
              "date": "2026-06-11",
              "sunshineDuration": 49427,
              "cloudCoverMean": 11
            },
            {
              "date": "2026-06-12",
              "sunshineDuration": 44500,
              "cloudCoverMean": 51
            },
            {
              "date": "2026-06-13",
              "sunshineDuration": 33683,
              "cloudCoverMean": 84
            },
            {
              "date": "2026-06-14",
              "sunshineDuration": 48383,
              "cloudCoverMean": 36
            }
          ]
        },
        "weatherScore": 57.4,
        "rollingGdd": 33,
        "gddBoost": 1.18,
        "precipitationPenalty": 0.78,
        "drynessWindBoost": 1.08,
        "sunshineBoost": 1.16,
        "cloudPenalty": 1,
        "sunnyStreakBoost": 1,
        "ecologyMultiplier": 1.06,
        "advice": "建议减少外出，尤其注意大型公园、滨河绿地和午后风口区域；外出请做好口鼻防护。"
      }
    },
    {
      "id": "changping",
      "name": "昌平区",
      "shortName": "昌平",
      "districtTag": "北部开阔",
      "districtHint": "开阔地配阵风时扩散更快",
      "score": 100,
      "level": {
        "key": "high",
        "label": "高风险"
      },
      "weather": {
        "date": "2026-06-12",
        "temperatureMax": 34.8,
        "temperatureMin": 17.7,
        "temperatureMean": 26.3,
        "humidity": 42,
        "humidityMin": 23,
        "windSpeed": 6.1,
        "windGust": 10.4,
        "precipitation": 0.2,
        "recentPrecipitation": 7.8,
        "sunshineDuration": 40687,
        "shortwaveRadiationSum": 23,
        "cloudCoverMean": 56,
        "rollingTemperatureMeans": [
          20.4,
          19.6,
          23.8,
          26.3
        ],
        "recentConditions": [
          {
            "date": "2026-06-09",
            "sunshineDuration": 49111,
            "cloudCoverMean": 20
          },
          {
            "date": "2026-06-10",
            "sunshineDuration": 39372,
            "cloudCoverMean": 57
          },
          {
            "date": "2026-06-11",
            "sunshineDuration": 49599,
            "cloudCoverMean": 7
          },
          {
            "date": "2026-06-12",
            "sunshineDuration": 40687,
            "cloudCoverMean": 56
          }
        ]
      },
      "weatherScore": 100,
      "rollingGdd": 30.1,
      "gddBoost": 1.18,
      "precipitationPenalty": 0.62,
      "drynessWindBoost": 1.16,
      "sunshineBoost": 1.16,
      "cloudPenalty": 0.93,
      "sunnyStreakBoost": 1,
      "ecologyMultiplier": 1.12,
      "hotspots": [
        "十三陵水库",
        "未来科学城滨水绿地"
      ],
      "advice": "建议减少外出，尤其注意大型公园、滨河绿地和午后风口区域；外出请做好口鼻防护。",
      "headline": "昌平区当前以气象条件和区级生态暴露驱动为主。",
      "tomorrow": {
        "score": 68.4,
        "level": {
          "key": "high",
          "label": "高风险"
        },
        "weather": {
          "date": "2026-06-13",
          "temperatureMax": 27.3,
          "temperatureMin": 19.1,
          "temperatureMean": 23.2,
          "humidity": 72,
          "humidityMin": 53,
          "windSpeed": 2.8,
          "windGust": 7.8,
          "precipitation": 3.7,
          "recentPrecipitation": 0.2,
          "sunshineDuration": 28247,
          "shortwaveRadiationSum": 16.6,
          "cloudCoverMean": 75,
          "rollingTemperatureMeans": [
            19.6,
            23.8,
            26.3,
            23.2
          ],
          "recentConditions": [
            {
              "date": "2026-06-10",
              "sunshineDuration": 39372,
              "cloudCoverMean": 57
            },
            {
              "date": "2026-06-11",
              "sunshineDuration": 49599,
              "cloudCoverMean": 7
            },
            {
              "date": "2026-06-12",
              "sunshineDuration": 40687,
              "cloudCoverMean": 56
            },
            {
              "date": "2026-06-13",
              "sunshineDuration": 28247,
              "cloudCoverMean": 75
            }
          ]
        },
        "weatherScore": 57.4,
        "rollingGdd": 32.9,
        "gddBoost": 1.18,
        "precipitationPenalty": 0.9,
        "drynessWindBoost": 1.04,
        "sunshineBoost": 1.12,
        "cloudPenalty": 0.86,
        "sunnyStreakBoost": 1,
        "ecologyMultiplier": 1.12,
        "advice": "建议减少外出，尤其注意大型公园、滨河绿地和午后风口区域；外出请做好口鼻防护。"
      },
      "dayAfterTomorrow": {
        "score": 69.3,
        "level": {
          "key": "high",
          "label": "高风险"
        },
        "weather": {
          "date": "2026-06-14",
          "temperatureMax": 30.5,
          "temperatureMin": 18.6,
          "temperatureMean": 24.3,
          "humidity": 71,
          "humidityMin": 43,
          "windSpeed": 2.9,
          "windGust": 8.7,
          "precipitation": 4.1,
          "recentPrecipitation": 3.9,
          "sunshineDuration": 46935,
          "shortwaveRadiationSum": 24,
          "cloudCoverMean": 40,
          "rollingTemperatureMeans": [
            23.8,
            26.3,
            23.2,
            24.3
          ],
          "recentConditions": [
            {
              "date": "2026-06-11",
              "sunshineDuration": 49599,
              "cloudCoverMean": 7
            },
            {
              "date": "2026-06-12",
              "sunshineDuration": 40687,
              "cloudCoverMean": 56
            },
            {
              "date": "2026-06-13",
              "sunshineDuration": 28247,
              "cloudCoverMean": 75
            },
            {
              "date": "2026-06-14",
              "sunshineDuration": 46935,
              "cloudCoverMean": 40
            }
          ]
        },
        "weatherScore": 65.1,
        "rollingGdd": 37.6,
        "gddBoost": 1.18,
        "precipitationPenalty": 0.62,
        "drynessWindBoost": 1.12,
        "sunshineBoost": 1.16,
        "cloudPenalty": 1,
        "sunnyStreakBoost": 1,
        "ecologyMultiplier": 1.12,
        "advice": "建议减少外出，尤其注意大型公园、滨河绿地和午后风口区域；外出请做好口鼻防护。"
      }
    },
    {
      "id": "daxing",
      "name": "大兴区",
      "shortName": "大兴",
      "districtTag": "南海湿地",
      "districtHint": "湿地周边雨后回升需关注",
      "score": 100,
      "level": {
        "key": "high",
        "label": "高风险"
      },
      "weather": {
        "date": "2026-06-12",
        "temperatureMax": 34.1,
        "temperatureMin": 21.1,
        "temperatureMean": 28.1,
        "humidity": 40,
        "humidityMin": 24,
        "windSpeed": 4.6,
        "windGust": 11.1,
        "precipitation": 0,
        "recentPrecipitation": 3.7,
        "sunshineDuration": 42037,
        "shortwaveRadiationSum": 23.9,
        "cloudCoverMean": 55,
        "rollingTemperatureMeans": [
          22.4,
          21.1,
          25,
          28.1
        ],
        "recentConditions": [
          {
            "date": "2026-06-09",
            "sunshineDuration": 48308,
            "cloudCoverMean": 18
          },
          {
            "date": "2026-06-10",
            "sunshineDuration": 45604,
            "cloudCoverMean": 43
          },
          {
            "date": "2026-06-11",
            "sunshineDuration": 49423,
            "cloudCoverMean": 9
          },
          {
            "date": "2026-06-12",
            "sunshineDuration": 42037,
            "cloudCoverMean": 55
          }
        ]
      },
      "weatherScore": 100,
      "rollingGdd": 36.6,
      "gddBoost": 1.18,
      "precipitationPenalty": 0.9,
      "drynessWindBoost": 1.16,
      "sunshineBoost": 1.16,
      "cloudPenalty": 0.93,
      "sunnyStreakBoost": 1,
      "ecologyMultiplier": 1.12,
      "hotspots": [
        "念坛公园",
        "南海子公园"
      ],
      "advice": "建议减少外出，尤其注意大型公园、滨河绿地和午后风口区域；外出请做好口鼻防护。",
      "headline": "大兴区当前以气象条件和区级生态暴露驱动为主。",
      "tomorrow": {
        "score": 91.2,
        "level": {
          "key": "high",
          "label": "高风险"
        },
        "weather": {
          "date": "2026-06-13",
          "temperatureMax": 29.7,
          "temperatureMin": 21,
          "temperatureMean": 24.8,
          "humidity": 62,
          "humidityMin": 42,
          "windSpeed": 5,
          "windGust": 9.8,
          "precipitation": 2.6,
          "recentPrecipitation": 0,
          "sunshineDuration": 36364,
          "shortwaveRadiationSum": 20.9,
          "cloudCoverMean": 75,
          "rollingTemperatureMeans": [
            21.1,
            25,
            28.1,
            24.8
          ],
          "recentConditions": [
            {
              "date": "2026-06-10",
              "sunshineDuration": 45604,
              "cloudCoverMean": 43
            },
            {
              "date": "2026-06-11",
              "sunshineDuration": 49423,
              "cloudCoverMean": 9
            },
            {
              "date": "2026-06-12",
              "sunshineDuration": 42037,
              "cloudCoverMean": 55
            },
            {
              "date": "2026-06-13",
              "sunshineDuration": 36364,
              "cloudCoverMean": 75
            }
          ]
        },
        "weatherScore": 68.6,
        "rollingGdd": 39,
        "gddBoost": 1.18,
        "precipitationPenalty": 0.9,
        "drynessWindBoost": 1.12,
        "sunshineBoost": 1.16,
        "cloudPenalty": 0.86,
        "sunnyStreakBoost": 1,
        "ecologyMultiplier": 1.12,
        "advice": "建议减少外出，尤其注意大型公园、滨河绿地和午后风口区域；外出请做好口鼻防护。"
      },
      "dayAfterTomorrow": {
        "score": 90,
        "level": {
          "key": "high",
          "label": "高风险"
        },
        "weather": {
          "date": "2026-06-14",
          "temperatureMax": 30.5,
          "temperatureMin": 19.7,
          "temperatureMean": 24.6,
          "humidity": 69,
          "humidityMin": 42,
          "windSpeed": 3.8,
          "windGust": 12.1,
          "precipitation": 2.8,
          "recentPrecipitation": 2.6,
          "sunshineDuration": 47693,
          "shortwaveRadiationSum": 24.6,
          "cloudCoverMean": 42,
          "rollingTemperatureMeans": [
            25,
            28.1,
            24.8,
            24.6
          ],
          "recentConditions": [
            {
              "date": "2026-06-11",
              "sunshineDuration": 49423,
              "cloudCoverMean": 9
            },
            {
              "date": "2026-06-12",
              "sunshineDuration": 42037,
              "cloudCoverMean": 55
            },
            {
              "date": "2026-06-13",
              "sunshineDuration": 36364,
              "cloudCoverMean": 75
            },
            {
              "date": "2026-06-14",
              "sunshineDuration": 47693,
              "cloudCoverMean": 42
            }
          ]
        },
        "weatherScore": 67.2,
        "rollingGdd": 42.5,
        "gddBoost": 1.18,
        "precipitationPenalty": 0.78,
        "drynessWindBoost": 1.12,
        "sunshineBoost": 1.16,
        "cloudPenalty": 1,
        "sunnyStreakBoost": 1,
        "ecologyMultiplier": 1.12,
        "advice": "建议减少外出，尤其注意大型公园、滨河绿地和午后风口区域；外出请做好口鼻防护。"
      }
    },
    {
      "id": "fangshan",
      "name": "房山区",
      "shortName": "房山",
      "districtTag": "河谷绿带",
      "districtHint": "河谷与新区绿化带更关键",
      "score": 100,
      "level": {
        "key": "high",
        "label": "高风险"
      },
      "weather": {
        "date": "2026-06-12",
        "temperatureMax": 35.1,
        "temperatureMin": 20.1,
        "temperatureMean": 28.5,
        "humidity": 38,
        "humidityMin": 23,
        "windSpeed": 4,
        "windGust": 10,
        "precipitation": 0,
        "recentPrecipitation": 3.3,
        "sunshineDuration": 41890,
        "shortwaveRadiationSum": 23.2,
        "cloudCoverMean": 57,
        "rollingTemperatureMeans": [
          22.8,
          21.4,
          25,
          28.5
        ],
        "recentConditions": [
          {
            "date": "2026-06-09",
            "sunshineDuration": 49059,
            "cloudCoverMean": 14
          },
          {
            "date": "2026-06-10",
            "sunshineDuration": 44146,
            "cloudCoverMean": 44
          },
          {
            "date": "2026-06-11",
            "sunshineDuration": 49504,
            "cloudCoverMean": 9
          },
          {
            "date": "2026-06-12",
            "sunshineDuration": 41890,
            "cloudCoverMean": 57
          }
        ]
      },
      "weatherScore": 100,
      "rollingGdd": 37.7,
      "gddBoost": 1.18,
      "precipitationPenalty": 0.9,
      "drynessWindBoost": 1.16,
      "sunshineBoost": 1.16,
      "cloudPenalty": 0.93,
      "sunnyStreakBoost": 1,
      "ecologyMultiplier": 1.04,
      "hotspots": [
        "长阳公园",
        "小清河沿线绿地"
      ],
      "advice": "建议减少外出，尤其注意大型公园、滨河绿地和午后风口区域；外出请做好口鼻防护。",
      "headline": "房山区当前以气象条件和区级生态暴露驱动为主。",
      "tomorrow": {
        "score": 100,
        "level": {
          "key": "high",
          "label": "高风险"
        },
        "weather": {
          "date": "2026-06-13",
          "temperatureMax": 31,
          "temperatureMin": 21.9,
          "temperatureMean": 25.5,
          "humidity": 59,
          "humidityMin": 40,
          "windSpeed": 3.7,
          "windGust": 10.1,
          "precipitation": 2.5,
          "recentPrecipitation": 0,
          "sunshineDuration": 36492,
          "shortwaveRadiationSum": 20.4,
          "cloudCoverMean": 74,
          "rollingTemperatureMeans": [
            21.4,
            25,
            28.5,
            25.5
          ],
          "recentConditions": [
            {
              "date": "2026-06-10",
              "sunshineDuration": 44146,
              "cloudCoverMean": 44
            },
            {
              "date": "2026-06-11",
              "sunshineDuration": 49504,
              "cloudCoverMean": 9
            },
            {
              "date": "2026-06-12",
              "sunshineDuration": 41890,
              "cloudCoverMean": 57
            },
            {
              "date": "2026-06-13",
              "sunshineDuration": 36492,
              "cloudCoverMean": 74
            }
          ]
        },
        "weatherScore": 100,
        "rollingGdd": 40.4,
        "gddBoost": 1.18,
        "precipitationPenalty": 0.9,
        "drynessWindBoost": 1.12,
        "sunshineBoost": 1.16,
        "cloudPenalty": 0.93,
        "sunnyStreakBoost": 1,
        "ecologyMultiplier": 1.04,
        "advice": "建议减少外出，尤其注意大型公园、滨河绿地和午后风口区域；外出请做好口鼻防护。"
      },
      "dayAfterTomorrow": {
        "score": 100,
        "level": {
          "key": "high",
          "label": "高风险"
        },
        "weather": {
          "date": "2026-06-14",
          "temperatureMax": 32.1,
          "temperatureMin": 20.2,
          "temperatureMean": 25.9,
          "humidity": 63,
          "humidityMin": 37,
          "windSpeed": 2.6,
          "windGust": 9.6,
          "precipitation": 0.6,
          "recentPrecipitation": 2.5,
          "sunshineDuration": 47662,
          "shortwaveRadiationSum": 25.4,
          "cloudCoverMean": 34,
          "rollingTemperatureMeans": [
            25,
            28.5,
            25.5,
            25.9
          ],
          "recentConditions": [
            {
              "date": "2026-06-11",
              "sunshineDuration": 49504,
              "cloudCoverMean": 9
            },
            {
              "date": "2026-06-12",
              "sunshineDuration": 41890,
              "cloudCoverMean": 57
            },
            {
              "date": "2026-06-13",
              "sunshineDuration": 36492,
              "cloudCoverMean": 74
            },
            {
              "date": "2026-06-14",
              "sunshineDuration": 47662,
              "cloudCoverMean": 34
            }
          ]
        },
        "weatherScore": 76.3,
        "rollingGdd": 44.9,
        "gddBoost": 1.18,
        "precipitationPenalty": 0.9,
        "drynessWindBoost": 1.12,
        "sunshineBoost": 1.16,
        "cloudPenalty": 1,
        "sunnyStreakBoost": 1,
        "ecologyMultiplier": 1.04,
        "advice": "建议减少外出，尤其注意大型公园、滨河绿地和午后风口区域；外出请做好口鼻防护。"
      }
    },
    {
      "id": "pinggu",
      "name": "平谷区",
      "shortName": "平谷",
      "districtTag": "郊野开阔",
      "districtHint": "郊野开阔地受天气驱动更强",
      "score": 100,
      "level": {
        "key": "high",
        "label": "高风险"
      },
      "weather": {
        "date": "2026-06-12",
        "temperatureMax": 32.6,
        "temperatureMin": 19,
        "temperatureMean": 25.6,
        "humidity": 46,
        "humidityMin": 27,
        "windSpeed": 5.4,
        "windGust": 9.3,
        "precipitation": 0,
        "recentPrecipitation": 5.3,
        "sunshineDuration": 43554,
        "shortwaveRadiationSum": 25.2,
        "cloudCoverMean": 44,
        "rollingTemperatureMeans": [
          18.7,
          18.5,
          22.2,
          25.6
        ],
        "recentConditions": [
          {
            "date": "2026-06-09",
            "sunshineDuration": 47964,
            "cloudCoverMean": 22
          },
          {
            "date": "2026-06-10",
            "sunshineDuration": 37907,
            "cloudCoverMean": 75
          },
          {
            "date": "2026-06-11",
            "sunshineDuration": 50154,
            "cloudCoverMean": 12
          },
          {
            "date": "2026-06-12",
            "sunshineDuration": 43554,
            "cloudCoverMean": 44
          }
        ]
      },
      "weatherScore": 100,
      "rollingGdd": 25,
      "gddBoost": 1.18,
      "precipitationPenalty": 0.78,
      "drynessWindBoost": 1.16,
      "sunshineBoost": 1.16,
      "cloudPenalty": 1,
      "sunnyStreakBoost": 1.06,
      "ecologyMultiplier": 0.93,
      "hotspots": [
        "金海湖周边绿地",
        "泃河沿线"
      ],
      "advice": "建议减少外出，尤其注意大型公园、滨河绿地和午后风口区域；外出请做好口鼻防护。",
      "headline": "平谷区当前以气象条件和区级生态暴露驱动为主。",
      "tomorrow": {
        "score": 28.2,
        "level": {
          "key": "low",
          "label": "低风险"
        },
        "weather": {
          "date": "2026-06-13",
          "temperatureMax": 25.2,
          "temperatureMin": 17.6,
          "temperatureMean": 20.9,
          "humidity": 82,
          "humidityMin": 62,
          "windSpeed": 5,
          "windGust": 11.5,
          "precipitation": 34.3,
          "recentPrecipitation": 0,
          "sunshineDuration": 27582,
          "shortwaveRadiationSum": 17.8,
          "cloudCoverMean": 86,
          "rollingTemperatureMeans": [
            18.5,
            22.2,
            25.6,
            20.9
          ],
          "recentConditions": [
            {
              "date": "2026-06-10",
              "sunshineDuration": 37907,
              "cloudCoverMean": 75
            },
            {
              "date": "2026-06-11",
              "sunshineDuration": 50154,
              "cloudCoverMean": 12
            },
            {
              "date": "2026-06-12",
              "sunshineDuration": 43554,
              "cloudCoverMean": 44
            },
            {
              "date": "2026-06-13",
              "sunshineDuration": 27582,
              "cloudCoverMean": 86
            }
          ]
        },
        "weatherScore": 41.3,
        "rollingGdd": 27.2,
        "gddBoost": 1.18,
        "precipitationPenalty": 0.62,
        "drynessWindBoost": 1.08,
        "sunshineBoost": 1.08,
        "cloudPenalty": 0.86,
        "sunnyStreakBoost": 1,
        "ecologyMultiplier": 0.93,
        "advice": "整体风险较低，但靠近公园、绿地和滨河区域时仍可能遇到局部飞絮。"
      },
      "dayAfterTomorrow": {
        "score": 34.7,
        "level": {
          "key": "medium",
          "label": "中风险"
        },
        "weather": {
          "date": "2026-06-14",
          "temperatureMax": 26.8,
          "temperatureMin": 17,
          "temperatureMean": 21.5,
          "humidity": 84,
          "humidityMin": 63,
          "windSpeed": 3.1,
          "windGust": 7.4,
          "precipitation": 2.9,
          "recentPrecipitation": 34.3,
          "sunshineDuration": 46013,
          "shortwaveRadiationSum": 20,
          "cloudCoverMean": 70,
          "rollingTemperatureMeans": [
            22.2,
            25.6,
            20.9,
            21.5
          ],
          "recentConditions": [
            {
              "date": "2026-06-11",
              "sunshineDuration": 50154,
              "cloudCoverMean": 12
            },
            {
              "date": "2026-06-12",
              "sunshineDuration": 43554,
              "cloudCoverMean": 44
            },
            {
              "date": "2026-06-13",
              "sunshineDuration": 27582,
              "cloudCoverMean": 86
            },
            {
              "date": "2026-06-14",
              "sunshineDuration": 46013,
              "cloudCoverMean": 70
            }
          ]
        },
        "weatherScore": 45.5,
        "rollingGdd": 30.2,
        "gddBoost": 1.18,
        "precipitationPenalty": 0.62,
        "drynessWindBoost": 1.04,
        "sunshineBoost": 1.16,
        "cloudPenalty": 0.93,
        "sunnyStreakBoost": 1,
        "ecologyMultiplier": 0.93,
        "advice": "建议避开 10:00-16:00 的长时间户外停留，经过公园或林地边缘时做好基础防护。"
      }
    },
    {
      "id": "miyun",
      "name": "密云区",
      "shortName": "密云",
      "districtTag": "库区风场",
      "districtHint": "库区周边更看风与湿度变化",
      "score": 100,
      "level": {
        "key": "high",
        "label": "高风险"
      },
      "weather": {
        "date": "2026-06-12",
        "temperatureMax": 32.7,
        "temperatureMin": 17.8,
        "temperatureMean": 25.4,
        "humidity": 48,
        "humidityMin": 28,
        "windSpeed": 4.8,
        "windGust": 11.2,
        "precipitation": 4.3,
        "recentPrecipitation": 3.4,
        "sunshineDuration": 43938,
        "shortwaveRadiationSum": 24.1,
        "cloudCoverMean": 52,
        "rollingTemperatureMeans": [
          19.3,
          19.1,
          22.1,
          25.4
        ],
        "recentConditions": [
          {
            "date": "2026-06-09",
            "sunshineDuration": 48136,
            "cloudCoverMean": 26
          },
          {
            "date": "2026-06-10",
            "sunshineDuration": 41684,
            "cloudCoverMean": 72
          },
          {
            "date": "2026-06-11",
            "sunshineDuration": 49986,
            "cloudCoverMean": 13
          },
          {
            "date": "2026-06-12",
            "sunshineDuration": 43938,
            "cloudCoverMean": 52
          }
        ]
      },
      "weatherScore": 100,
      "rollingGdd": 25.9,
      "gddBoost": 1.18,
      "precipitationPenalty": 0.78,
      "drynessWindBoost": 1.16,
      "sunshineBoost": 1.16,
      "cloudPenalty": 1,
      "sunnyStreakBoost": 1,
      "ecologyMultiplier": 0.94,
      "hotspots": [
        "密云水库周边",
        "白河沿线绿地"
      ],
      "advice": "建议减少外出，尤其注意大型公园、滨河绿地和午后风口区域；外出请做好口鼻防护。",
      "headline": "密云区当前以气象条件和区级生态暴露驱动为主。",
      "tomorrow": {
        "score": 31,
        "level": {
          "key": "medium",
          "label": "中风险"
        },
        "weather": {
          "date": "2026-06-13",
          "temperatureMax": 25.9,
          "temperatureMin": 18.7,
          "temperatureMean": 21.2,
          "humidity": 86,
          "humidityMin": 58,
          "windSpeed": 4.6,
          "windGust": 9.2,
          "precipitation": 20.9,
          "recentPrecipitation": 4.3,
          "sunshineDuration": 29747,
          "shortwaveRadiationSum": 17.6,
          "cloudCoverMean": 88,
          "rollingTemperatureMeans": [
            19.1,
            22.1,
            25.4,
            21.2
          ],
          "recentConditions": [
            {
              "date": "2026-06-10",
              "sunshineDuration": 41684,
              "cloudCoverMean": 72
            },
            {
              "date": "2026-06-11",
              "sunshineDuration": 49986,
              "cloudCoverMean": 13
            },
            {
              "date": "2026-06-12",
              "sunshineDuration": 43938,
              "cloudCoverMean": 52
            },
            {
              "date": "2026-06-13",
              "sunshineDuration": 29747,
              "cloudCoverMean": 88
            }
          ]
        },
        "weatherScore": 43.4,
        "rollingGdd": 27.8,
        "gddBoost": 1.18,
        "precipitationPenalty": 0.62,
        "drynessWindBoost": 1.08,
        "sunshineBoost": 1.12,
        "cloudPenalty": 0.86,
        "sunnyStreakBoost": 1,
        "ecologyMultiplier": 0.94,
        "advice": "建议避开 10:00-16:00 的长时间户外停留，经过公园或林地边缘时做好基础防护。"
      },
      "dayAfterTomorrow": {
        "score": 46.4,
        "level": {
          "key": "medium",
          "label": "中风险"
        },
        "weather": {
          "date": "2026-06-14",
          "temperatureMax": 28.2,
          "temperatureMin": 18.8,
          "temperatureMean": 22.7,
          "humidity": 79,
          "humidityMin": 52,
          "windSpeed": 2.5,
          "windGust": 9.5,
          "precipitation": 0.9,
          "recentPrecipitation": 25.2,
          "sunshineDuration": 47368,
          "shortwaveRadiationSum": 23.5,
          "cloudCoverMean": 54,
          "rollingTemperatureMeans": [
            22.1,
            25.4,
            21.2,
            22.7
          ],
          "recentConditions": [
            {
              "date": "2026-06-11",
              "sunshineDuration": 49986,
              "cloudCoverMean": 13
            },
            {
              "date": "2026-06-12",
              "sunshineDuration": 43938,
              "cloudCoverMean": 52
            },
            {
              "date": "2026-06-13",
              "sunshineDuration": 29747,
              "cloudCoverMean": 88
            },
            {
              "date": "2026-06-14",
              "sunshineDuration": 47368,
              "cloudCoverMean": 54
            }
          ]
        },
        "weatherScore": 53.9,
        "rollingGdd": 31.4,
        "gddBoost": 1.18,
        "precipitationPenalty": 0.62,
        "drynessWindBoost": 1.08,
        "sunshineBoost": 1.16,
        "cloudPenalty": 1,
        "sunnyStreakBoost": 1,
        "ecologyMultiplier": 0.94,
        "advice": "建议避开 10:00-16:00 的长时间户外停留，经过公园或林地边缘时做好基础防护。"
      }
    },
    {
      "id": "shijingshan",
      "name": "石景山区",
      "shortName": "石景山",
      "districtTag": "西山风口",
      "districtHint": "山前风口让飘散感更明显",
      "score": 98.9,
      "level": {
        "key": "high",
        "label": "高风险"
      },
      "weather": {
        "date": "2026-06-12",
        "temperatureMax": 34.3,
        "temperatureMin": 19.3,
        "temperatureMean": 27.5,
        "humidity": 40,
        "humidityMin": 22,
        "windSpeed": 4.1,
        "windGust": 10.3,
        "precipitation": 1.4,
        "recentPrecipitation": 8.4,
        "sunshineDuration": 40081,
        "shortwaveRadiationSum": 23.2,
        "cloudCoverMean": 60,
        "rollingTemperatureMeans": [
          22,
          20.7,
          24.4,
          27.5
        ],
        "recentConditions": [
          {
            "date": "2026-06-09",
            "sunshineDuration": 49193,
            "cloudCoverMean": 12
          },
          {
            "date": "2026-06-10",
            "sunshineDuration": 45677,
            "cloudCoverMean": 45
          },
          {
            "date": "2026-06-11",
            "sunshineDuration": 49690,
            "cloudCoverMean": 8
          },
          {
            "date": "2026-06-12",
            "sunshineDuration": 40081,
            "cloudCoverMean": 60
          }
        ]
      },
      "weatherScore": 100,
      "rollingGdd": 34.6,
      "gddBoost": 1.18,
      "precipitationPenalty": 0.62,
      "drynessWindBoost": 1.16,
      "sunshineBoost": 1.16,
      "cloudPenalty": 0.93,
      "sunnyStreakBoost": 1,
      "ecologyMultiplier": 1.08,
      "hotspots": [
        "八大处公园",
        "永定河休闲森林公园"
      ],
      "advice": "建议减少外出，尤其注意大型公园、滨河绿地和午后风口区域；外出请做好口鼻防护。",
      "headline": "石景山区当前以气象条件和区级生态暴露驱动为主。",
      "tomorrow": {
        "score": 73.1,
        "level": {
          "key": "high",
          "label": "高风险"
        },
        "weather": {
          "date": "2026-06-13",
          "temperatureMax": 29.3,
          "temperatureMin": 20.8,
          "temperatureMean": 24,
          "humidity": 65,
          "humidityMin": 45,
          "windSpeed": 3,
          "windGust": 12.6,
          "precipitation": 2.9,
          "recentPrecipitation": 1.4,
          "sunshineDuration": 34467,
          "shortwaveRadiationSum": 19.3,
          "cloudCoverMean": 73,
          "rollingTemperatureMeans": [
            20.7,
            24.4,
            27.5,
            24
          ],
          "recentConditions": [
            {
              "date": "2026-06-10",
              "sunshineDuration": 45677,
              "cloudCoverMean": 45
            },
            {
              "date": "2026-06-11",
              "sunshineDuration": 49690,
              "cloudCoverMean": 8
            },
            {
              "date": "2026-06-12",
              "sunshineDuration": 40081,
              "cloudCoverMean": 60
            },
            {
              "date": "2026-06-13",
              "sunshineDuration": 34467,
              "cloudCoverMean": 73
            }
          ]
        },
        "weatherScore": 63,
        "rollingGdd": 36.6,
        "gddBoost": 1.18,
        "precipitationPenalty": 0.78,
        "drynessWindBoost": 1.12,
        "sunshineBoost": 1.12,
        "cloudPenalty": 0.93,
        "sunnyStreakBoost": 1,
        "ecologyMultiplier": 1.08,
        "advice": "建议减少外出，尤其注意大型公园、滨河绿地和午后风口区域；外出请做好口鼻防护。"
      },
      "dayAfterTomorrow": {
        "score": 86.8,
        "level": {
          "key": "high",
          "label": "高风险"
        },
        "weather": {
          "date": "2026-06-14",
          "temperatureMax": 30.1,
          "temperatureMin": 19.5,
          "temperatureMean": 24.6,
          "humidity": 68,
          "humidityMin": 42,
          "windSpeed": 2.3,
          "windGust": 9.1,
          "precipitation": 2.3,
          "recentPrecipitation": 4.3,
          "sunshineDuration": 47663,
          "shortwaveRadiationSum": 25.2,
          "cloudCoverMean": 43,
          "rollingTemperatureMeans": [
            24.4,
            27.5,
            24,
            24.6
          ],
          "recentConditions": [
            {
              "date": "2026-06-11",
              "sunshineDuration": 49690,
              "cloudCoverMean": 8
            },
            {
              "date": "2026-06-12",
              "sunshineDuration": 40081,
              "cloudCoverMean": 60
            },
            {
              "date": "2026-06-13",
              "sunshineDuration": 34467,
              "cloudCoverMean": 73
            },
            {
              "date": "2026-06-14",
              "sunshineDuration": 47663,
              "cloudCoverMean": 43
            }
          ]
        },
        "weatherScore": 67.2,
        "rollingGdd": 40.5,
        "gddBoost": 1.18,
        "precipitationPenalty": 0.78,
        "drynessWindBoost": 1.12,
        "sunshineBoost": 1.16,
        "cloudPenalty": 1,
        "sunnyStreakBoost": 1,
        "ecologyMultiplier": 1.08,
        "advice": "建议减少外出，尤其注意大型公园、滨河绿地和午后风口区域；外出请做好口鼻防护。"
      }
    },
    {
      "id": "mentougou",
      "name": "门头沟区",
      "shortName": "门头沟",
      "districtTag": "山谷通道",
      "districtHint": "山前通风通道影响体感强弱",
      "score": 89.7,
      "level": {
        "key": "high",
        "label": "高风险"
      },
      "weather": {
        "date": "2026-06-12",
        "temperatureMax": 33.1,
        "temperatureMin": 15.7,
        "temperatureMean": 25.3,
        "humidity": 52,
        "humidityMin": 26,
        "windSpeed": 3.9,
        "windGust": 10.9,
        "precipitation": 0.4,
        "recentPrecipitation": 9.9,
        "sunshineDuration": 40840,
        "shortwaveRadiationSum": 23.1,
        "cloudCoverMean": 62,
        "rollingTemperatureMeans": [
          20.7,
          18.9,
          23.1,
          25.3
        ],
        "recentConditions": [
          {
            "date": "2026-06-09",
            "sunshineDuration": 49515,
            "cloudCoverMean": 16
          },
          {
            "date": "2026-06-10",
            "sunshineDuration": 45792,
            "cloudCoverMean": 44
          },
          {
            "date": "2026-06-11",
            "sunshineDuration": 49752,
            "cloudCoverMean": 10
          },
          {
            "date": "2026-06-12",
            "sunshineDuration": 40840,
            "cloudCoverMean": 62
          }
        ]
      },
      "weatherScore": 100,
      "rollingGdd": 28,
      "gddBoost": 1.18,
      "precipitationPenalty": 0.62,
      "drynessWindBoost": 1.16,
      "sunshineBoost": 1.16,
      "cloudPenalty": 0.93,
      "sunnyStreakBoost": 1,
      "ecologyMultiplier": 0.98,
      "hotspots": [
        "永定河沿线",
        "潭柘寺周边绿地"
      ],
      "advice": "建议减少外出，尤其注意大型公园、滨河绿地和午后风口区域；外出请做好口鼻防护。",
      "headline": "门头沟区当前以气象条件和区级生态暴露驱动为主。",
      "tomorrow": {
        "score": 65.6,
        "level": {
          "key": "high",
          "label": "高风险"
        },
        "weather": {
          "date": "2026-06-13",
          "temperatureMax": 28,
          "temperatureMin": 19.4,
          "temperatureMean": 23,
          "humidity": 72,
          "humidityMin": 50,
          "windSpeed": 3.1,
          "windGust": 11,
          "precipitation": 2.7,
          "recentPrecipitation": 0.4,
          "sunshineDuration": 36892,
          "shortwaveRadiationSum": 19.2,
          "cloudCoverMean": 71,
          "rollingTemperatureMeans": [
            18.9,
            23.1,
            25.3,
            23
          ],
          "recentConditions": [
            {
              "date": "2026-06-10",
              "sunshineDuration": 45792,
              "cloudCoverMean": 44
            },
            {
              "date": "2026-06-11",
              "sunshineDuration": 49752,
              "cloudCoverMean": 10
            },
            {
              "date": "2026-06-12",
              "sunshineDuration": 40840,
              "cloudCoverMean": 62
            },
            {
              "date": "2026-06-13",
              "sunshineDuration": 36892,
              "cloudCoverMean": 71
            }
          ]
        },
        "weatherScore": 56,
        "rollingGdd": 30.3,
        "gddBoost": 1.18,
        "precipitationPenalty": 0.9,
        "drynessWindBoost": 1.08,
        "sunshineBoost": 1.12,
        "cloudPenalty": 0.93,
        "sunnyStreakBoost": 1,
        "ecologyMultiplier": 0.98,
        "advice": "建议减少外出，尤其注意大型公园、滨河绿地和午后风口区域；外出请做好口鼻防护。"
      },
      "dayAfterTomorrow": {
        "score": 74.6,
        "level": {
          "key": "high",
          "label": "高风险"
        },
        "weather": {
          "date": "2026-06-14",
          "temperatureMax": 29.7,
          "temperatureMin": 18.4,
          "temperatureMean": 24.1,
          "humidity": 71,
          "humidityMin": 45,
          "windSpeed": 2.6,
          "windGust": 9.9,
          "precipitation": 1.9,
          "recentPrecipitation": 3.1,
          "sunshineDuration": 47989,
          "shortwaveRadiationSum": 25.4,
          "cloudCoverMean": 42,
          "rollingTemperatureMeans": [
            23.1,
            25.3,
            23,
            24.1
          ],
          "recentConditions": [
            {
              "date": "2026-06-11",
              "sunshineDuration": 49752,
              "cloudCoverMean": 10
            },
            {
              "date": "2026-06-12",
              "sunshineDuration": 40840,
              "cloudCoverMean": 62
            },
            {
              "date": "2026-06-13",
              "sunshineDuration": 36892,
              "cloudCoverMean": 71
            },
            {
              "date": "2026-06-14",
              "sunshineDuration": 47989,
              "cloudCoverMean": 42
            }
          ]
        },
        "weatherScore": 63.7,
        "rollingGdd": 35.5,
        "gddBoost": 1.18,
        "precipitationPenalty": 0.78,
        "drynessWindBoost": 1.12,
        "sunshineBoost": 1.16,
        "cloudPenalty": 1,
        "sunnyStreakBoost": 1,
        "ecologyMultiplier": 0.98,
        "advice": "建议减少外出，尤其注意大型公园、滨河绿地和午后风口区域；外出请做好口鼻防护。"
      }
    },
    {
      "id": "huairou",
      "name": "怀柔区",
      "shortName": "怀柔",
      "districtTag": "湖区林地",
      "districtHint": "湖区林地局部波动更大",
      "score": 62.9,
      "level": {
        "key": "high",
        "label": "高风险"
      },
      "weather": {
        "date": "2026-06-12",
        "temperatureMax": 30.5,
        "temperatureMin": 16.8,
        "temperatureMean": 23.5,
        "humidity": 61,
        "humidityMin": 42,
        "windSpeed": 4.5,
        "windGust": 11.3,
        "precipitation": 0.3,
        "recentPrecipitation": 5.4,
        "sunshineDuration": 45153,
        "shortwaveRadiationSum": 24.1,
        "cloudCoverMean": 57,
        "rollingTemperatureMeans": [
          19.1,
          18,
          21.1,
          23.5
        ],
        "recentConditions": [
          {
            "date": "2026-06-09",
            "sunshineDuration": 48435,
            "cloudCoverMean": 27
          },
          {
            "date": "2026-06-10",
            "sunshineDuration": 39638,
            "cloudCoverMean": 71
          },
          {
            "date": "2026-06-11",
            "sunshineDuration": 49658,
            "cloudCoverMean": 16
          },
          {
            "date": "2026-06-12",
            "sunshineDuration": 45153,
            "cloudCoverMean": 57
          }
        ]
      },
      "weatherScore": 59.5,
      "rollingGdd": 21.7,
      "gddBoost": 1.18,
      "precipitationPenalty": 0.78,
      "drynessWindBoost": 1.12,
      "sunshineBoost": 1.16,
      "cloudPenalty": 0.93,
      "sunnyStreakBoost": 1,
      "ecologyMultiplier": 0.95,
      "hotspots": [
        "红螺湖公园",
        "雁栖湖周边"
      ],
      "advice": "建议减少外出，尤其注意大型公园、滨河绿地和午后风口区域；外出请做好口鼻防护。",
      "headline": "怀柔区当前以气象条件和区级生态暴露驱动为主。",
      "tomorrow": {
        "score": 37.8,
        "level": {
          "key": "medium",
          "label": "中风险"
        },
        "weather": {
          "date": "2026-06-13",
          "temperatureMax": 26.5,
          "temperatureMin": 18.1,
          "temperatureMean": 21.4,
          "humidity": 83,
          "humidityMin": 59,
          "windSpeed": 3.7,
          "windGust": 7.3,
          "precipitation": 6.4,
          "recentPrecipitation": 0.3,
          "sunshineDuration": 27264,
          "shortwaveRadiationSum": 16.7,
          "cloudCoverMean": 88,
          "rollingTemperatureMeans": [
            18,
            21.1,
            23.5,
            21.4
          ],
          "recentConditions": [
            {
              "date": "2026-06-10",
              "sunshineDuration": 39638,
              "cloudCoverMean": 71
            },
            {
              "date": "2026-06-11",
              "sunshineDuration": 49658,
              "cloudCoverMean": 16
            },
            {
              "date": "2026-06-12",
              "sunshineDuration": 45153,
              "cloudCoverMean": 57
            },
            {
              "date": "2026-06-13",
              "sunshineDuration": 27264,
              "cloudCoverMean": 88
            }
          ]
        },
        "weatherScore": 44.8,
        "rollingGdd": 24,
        "gddBoost": 1.18,
        "precipitationPenalty": 0.78,
        "drynessWindBoost": 1.04,
        "sunshineBoost": 1.08,
        "cloudPenalty": 0.86,
        "sunnyStreakBoost": 1,
        "ecologyMultiplier": 0.95,
        "advice": "建议避开 10:00-16:00 的长时间户外停留，经过公园或林地边缘时做好基础防护。"
      },
      "dayAfterTomorrow": {
        "score": 44,
        "level": {
          "key": "medium",
          "label": "中风险"
        },
        "weather": {
          "date": "2026-06-14",
          "temperatureMax": 28.3,
          "temperatureMin": 16.9,
          "temperatureMean": 22.5,
          "humidity": 81,
          "humidityMin": 54,
          "windSpeed": 2.4,
          "windGust": 7,
          "precipitation": 3.2,
          "recentPrecipitation": 6.7,
          "sunshineDuration": 48371,
          "shortwaveRadiationSum": 24.9,
          "cloudCoverMean": 48,
          "rollingTemperatureMeans": [
            21.1,
            23.5,
            21.4,
            22.5
          ],
          "recentConditions": [
            {
              "date": "2026-06-11",
              "sunshineDuration": 49658,
              "cloudCoverMean": 16
            },
            {
              "date": "2026-06-12",
              "sunshineDuration": 45153,
              "cloudCoverMean": 57
            },
            {
              "date": "2026-06-13",
              "sunshineDuration": 27264,
              "cloudCoverMean": 88
            },
            {
              "date": "2026-06-14",
              "sunshineDuration": 48371,
              "cloudCoverMean": 48
            }
          ]
        },
        "weatherScore": 52.5,
        "rollingGdd": 28.5,
        "gddBoost": 1.18,
        "precipitationPenalty": 0.62,
        "drynessWindBoost": 1.04,
        "sunshineBoost": 1.16,
        "cloudPenalty": 1,
        "sunnyStreakBoost": 1,
        "ecologyMultiplier": 0.95,
        "advice": "建议避开 10:00-16:00 的长时间户外停留，经过公园或林地边缘时做好基础防护。"
      }
    },
    {
      "id": "yanqing",
      "name": "延庆区",
      "shortName": "延庆",
      "districtTag": "高地晴风",
      "districtHint": "高地晴天阵风会放大飘散感",
      "score": 29.1,
      "level": {
        "key": "low",
        "label": "低风险"
      },
      "weather": {
        "date": "2026-06-12",
        "temperatureMax": 27.7,
        "temperatureMin": 13.6,
        "temperatureMean": 20.6,
        "humidity": 63,
        "humidityMin": 43,
        "windSpeed": 4,
        "windGust": 8.1,
        "precipitation": 1.1,
        "recentPrecipitation": 7.3,
        "sunshineDuration": 42238,
        "shortwaveRadiationSum": 22.7,
        "cloudCoverMean": 63,
        "rollingTemperatureMeans": [
          15.3,
          14.8,
          17.9,
          20.6
        ],
        "recentConditions": [
          {
            "date": "2026-06-09",
            "sunshineDuration": 49853,
            "cloudCoverMean": 29
          },
          {
            "date": "2026-06-10",
            "sunshineDuration": 43813,
            "cloudCoverMean": 58
          },
          {
            "date": "2026-06-11",
            "sunshineDuration": 50551,
            "cloudCoverMean": 16
          },
          {
            "date": "2026-06-12",
            "sunshineDuration": 42238,
            "cloudCoverMean": 63
          }
        ]
      },
      "weatherScore": 39.2,
      "rollingGdd": 8.8,
      "gddBoost": 1.09,
      "precipitationPenalty": 0.62,
      "drynessWindBoost": 1.12,
      "sunshineBoost": 1.16,
      "cloudPenalty": 0.93,
      "sunnyStreakBoost": 1,
      "ecologyMultiplier": 0.91,
      "hotspots": [
        "妫河森林公园",
        "世园公园"
      ],
      "advice": "整体风险较低，但靠近公园、绿地和滨河区域时仍可能遇到局部飞絮。",
      "headline": "延庆区当前以气象条件和区级生态暴露驱动为主。",
      "tomorrow": {
        "score": 21.3,
        "level": {
          "key": "low",
          "label": "低风险"
        },
        "weather": {
          "date": "2026-06-13",
          "temperatureMax": 22.6,
          "temperatureMin": 14.4,
          "temperatureMean": 18.4,
          "humidity": 86,
          "humidityMin": 67,
          "windSpeed": 3.6,
          "windGust": 9.4,
          "precipitation": 4.7,
          "recentPrecipitation": 1.1,
          "sunshineDuration": 38432,
          "shortwaveRadiationSum": 19.2,
          "cloudCoverMean": 69,
          "rollingTemperatureMeans": [
            14.8,
            17.9,
            20.6,
            18.4
          ],
          "recentConditions": [
            {
              "date": "2026-06-10",
              "sunshineDuration": 43813,
              "cloudCoverMean": 58
            },
            {
              "date": "2026-06-11",
              "sunshineDuration": 50551,
              "cloudCoverMean": 16
            },
            {
              "date": "2026-06-12",
              "sunshineDuration": 42238,
              "cloudCoverMean": 63
            },
            {
              "date": "2026-06-13",
              "sunshineDuration": 38432,
              "cloudCoverMean": 69
            }
          ]
        },
        "weatherScore": 23.8,
        "rollingGdd": 11.9,
        "gddBoost": 1.12,
        "precipitationPenalty": 0.78,
        "drynessWindBoost": 1.08,
        "sunshineBoost": 1.12,
        "cloudPenalty": 0.93,
        "sunnyStreakBoost": 1,
        "ecologyMultiplier": 0.91,
        "advice": "整体风险较低，但靠近公园、绿地和滨河区域时仍可能遇到局部飞絮。"
      },
      "dayAfterTomorrow": {
        "score": 28,
        "level": {
          "key": "low",
          "label": "低风险"
        },
        "weather": {
          "date": "2026-06-14",
          "temperatureMax": 26.8,
          "temperatureMin": 15.6,
          "temperatureMean": 20.4,
          "humidity": 76,
          "humidityMin": 47,
          "windSpeed": 1.5,
          "windGust": 7.3,
          "precipitation": 3.4,
          "recentPrecipitation": 5.8,
          "sunshineDuration": 47153,
          "shortwaveRadiationSum": 23.9,
          "cloudCoverMean": 65,
          "rollingTemperatureMeans": [
            17.9,
            20.6,
            18.4,
            20.4
          ],
          "recentConditions": [
            {
              "date": "2026-06-11",
              "sunshineDuration": 50551,
              "cloudCoverMean": 16
            },
            {
              "date": "2026-06-12",
              "sunshineDuration": 42238,
              "cloudCoverMean": 63
            },
            {
              "date": "2026-06-13",
              "sunshineDuration": 38432,
              "cloudCoverMean": 69
            },
            {
              "date": "2026-06-14",
              "sunshineDuration": 47153,
              "cloudCoverMean": 65
            }
          ]
        },
        "weatherScore": 37.8,
        "rollingGdd": 17.3,
        "gddBoost": 1.17,
        "precipitationPenalty": 0.62,
        "drynessWindBoost": 1.04,
        "sunshineBoost": 1.16,
        "cloudPenalty": 0.93,
        "sunnyStreakBoost": 1,
        "ecologyMultiplier": 0.91,
        "advice": "整体风险较低，但靠近公园、绿地和滨河区域时仍可能遇到局部飞絮。"
      }
    }
  ]
}
